circle_asset/version.py
circle_asset/circle_api.py
circle_asset/cli.py
circle_asset/__init__.py
circle_asset/project.py
circle_asset-0.0.6.dist-info/WHEEL
circle_asset-0.0.6.dist-info/DESCRIPTION.rst
circle_asset-0.0.6.dist-info/entry_points.txt
circle_asset-0.0.6.dist-info/METADATA
circle_asset-0.0.6.dist-info/metadata.json
circle_asset-0.0.6.dist-info/zip-safe
circle_asset-0.0.6.dist-info/top_level.txt
circle_asset-0.0.6.dist-info/RECORD
