Metadata-Version: 2.0
Name: circle-asset
Version: 0.0.6
Summary: Get the latest assets from CircleCI
Home-page: https://github.com/prophile/circle-asset
Author: Alistair Lynn
Author-email: arplynn@gmail.com
License: MIT
Platform: UNKNOWN
Classifier: Development Status :: 3 - Alpha
Classifier: Intended Audience :: Developers
Classifier: Intended Audience :: System Administrators
Classifier: License :: OSI Approved :: MIT License
Classifier: Programming Language :: Python :: 3.3
Classifier: Programming Language :: Python :: 3.4
Classifier: Topic :: Software Development :: Testing
Classifier: Topic :: System :: Installation/Setup
Requires-Dist: requests (>=2.5,<3)
